molter/__init__.py
molter/command.py
molter/converters.py
molter/errors.py
molter/help.py
molter/overrides.py
molter-0.11.0.dist-info/LICENSE
molter-0.11.0.dist-info/METADATA
molter-0.11.0.dist-info/WHEEL
molter-0.11.0.dist-info/top_level.txt
molter-0.11.0.dist-info/RECORD
